README.rst
setup.cfg
setup.py
stripe_django/__about__.py
stripe_django/__init__.py
stripe_django/apps.py
stripe_django/settings.py
stripe_django/utils.py
stripe_django.egg-info/PKG-INFO
stripe_django.egg-info/SOURCES.txt
stripe_django.egg-info/dependency_links.txt
stripe_django.egg-info/not-zip-safe
stripe_django.egg-info/requires.txt
stripe_django.egg-info/top_level.txt