Metadata-Version: 1.1
Name: stripe-django
Version: 0.1
Summary: tmux session manager
Home-page: http://github.com/develtech/stripe_django/
Author: Tony Narlock
Author-email: tony@git-pull.com
License: BSD
Download-URL: https://pypi.python.org/pypi/stripe_django
Keywords: stripe-django
Platform: UNKNOWN
Classifier: Development Status :: 5 - Production/Stable
Classifier: License :: OSI Approved :: BSD License
Classifier: Operating System :: POSIX
Classifier: Operating System :: MacOS :: MacOS X
Classifier: Environment :: Web Environment
Classifier: Intended Audience :: Developers
Classifier: Programming Language :: Python
Classifier: Programming Language :: Python :: 2.7
Classifier: Programming Language :: Python :: 3.3
Classifier: Programming Language :: Python :: 3.4
Classifier: Programming Language :: Python :: 3.5
